st_excel_table/__init__.py
st_excel_table/frontend/build/asset-manifest.json
st_excel_table/frontend/build/bootstrap.min.css
st_excel_table/frontend/build/index.html
st_excel_table/frontend/build/static/js/2.88f3d2a4.chunk.js
st_excel_table/frontend/build/static/js/2.88f3d2a4.chunk.js.LICENSE.txt
st_excel_table/frontend/build/static/js/2.88f3d2a4.chunk.js.map
st_excel_table/frontend/build/static/js/main.fd473ec4.chunk.js
st_excel_table/frontend/build/static/js/main.fd473ec4.chunk.js.map
st_excel_table/frontend/build/static/js/runtime-main.16d6c2f2.js
st_excel_table/frontend/build/static/js/runtime-main.16d6c2f2.js.map
streamlit_excel_table-0.2.3.dist-info/LICENSE
streamlit_excel_table-0.2.3.dist-info/METADATA
streamlit_excel_table-0.2.3.dist-info/WHEEL
streamlit_excel_table-0.2.3.dist-info/top_level.txt
streamlit_excel_table-0.2.3.dist-info/RECORD
