Metadata-Version: 2.1
Name: streamlit-excel-table
Version: 0.2.3
Summary: Streamlit component implementation of react-awesome-table
Home-page: https://github.com/tk42/streamlit-excel-table
Author: tk42
Author-email: nsplat+pip@gmail.com
Requires-Python: >=3.6
License-File: LICENSE
Requires-Dist: streamlit (>=0.63)
